shmipa/models.json
shmipa/shmart_phonemizer.py
shmipa-0.0.2.dist-info/LICENSE
shmipa-0.0.2.dist-info/METADATA
shmipa-0.0.2.dist-info/WHEEL
shmipa-0.0.2.dist-info/top_level.txt
shmipa-0.0.2.dist-info/RECORD
